cioclarisse/VERSION
cioclarisse/__init__.py
cioclarisse/attr_docs.py
cioclarisse/clarisse_config.py
cioclarisse/conductor_job.py
cioclarisse/const.py
cioclarisse/debug_ui.py
cioclarisse/dependencies.py
cioclarisse/environment_ui.py
cioclarisse/extra_uploads_ui.py
cioclarisse/frames_ui.py
cioclarisse/instances_ui.py
cioclarisse/metadata_ui.py
cioclarisse/notifications_ui.py
cioclarisse/post_install.py
cioclarisse/preview_ui.py
cioclarisse/projects_ui.py
cioclarisse/refresh.py
cioclarisse/reloader.py
cioclarisse/software_ui.py
cioclarisse/startup.py
cioclarisse/submission.py
cioclarisse/submit_actions.py
cioclarisse/task.py
cioclarisse/utils.py
cioclarisse/validation.py
cioclarisse/validation_ui.py
cioclarisse/scripts/ciocnode
cioclarisse/scripts/cioprep.py
cioclarisse-0.3.2.dist-info/METADATA
cioclarisse-0.3.2.dist-info/WHEEL
cioclarisse-0.3.2.dist-info/top_level.txt
cioclarisse-0.3.2.dist-info/RECORD
