Metadata-Version: 2.1
Name: cioclarisse
Version: 0.3.2
Summary: Clarisse plugin for Conductor Cloud Rendering Platform.
Home-page: https://github.com/ConductorTechnologies/cioclarisse
Author: conductor
Author-email: info@conductortech.com
License: UNKNOWN
Platform: UNKNOWN
Classifier: Operating System :: OS Independent
Classifier: Programming Language :: Python
Classifier: Topic :: Multimedia :: Graphics :: 3D Rendering
Requires-Dist: certifi (==2019.11.28)
Requires-Dist: ciocore (<5.0.0,>=4.0.6)
Requires-Dist: ciopath (<2.0.0,>=1.0.2)
Requires-Dist: cioseq (<1.0.0,>=0.1.13)
Requires-Dist: ciotemplate (<1.0.0,>=0.1.2)
